{
  "sentences": [
    {
      "en": "He remained optimistic despite the grim prognosis from his doctors.",
      "pt": "Ele permaneceu otimista apesar do prognóstico sombrio de seus médicos."
    },
    {
      "en": "The festival proceeded despite the severe weather warnings issued earlier.",
      "pt": "O festival prosseguiu apesar dos alertas de mau tempo emitidos anteriormente."
    },
    {
      "en": "She excelled in the role despite her lack of formal training.",
      "pt": "Ela se destacou no papel apesar de sua falta de treinamento formal."
    },
    {
      "en": "Despite his wealth, he lives a remarkably frugal and modest life.",
      "pt": "Apesar de sua riqueza, ele vive uma vida notavelmente frugal e modesta."
    },
    {
      "en": "The project was completed on time despite numerous logistical setbacks.",
      "pt": "O projeto foi concluído no prazo, apesar de inúmeros contratempos logísticos."
    },
    {
      "en": "She maintained her composure despite the aggressive questioning from the press.",
      "pt": "Ela manteve a compostura apesar do questionamento agressivo da imprensa."
    },
    {
      "en": "He refused to compromise his principles despite the immense pressure.",
      "pt": "Ele se recusou a comprometer seus princípios, apesar da imensa pressão."
    },
    {
      "en": "The economy grew slowly despite the global financial downturn.",
      "pt": "A economia cresceu lentamente apesar da recessão financeira global."
    },
    {
      "en": "They forged ahead with the merger despite opposition from shareholders.",
      "pt": "Eles avançaram com a fusão apesar da oposição dos acionistas."
    },
    {
      "en": "Despite the evidence, the jury found the defendant not guilty.",
      "pt": "Apesar das evidências, o júri considerou o réu inocente."
    },
    {
      "en": "She smiled warmly despite the obvious pain she was enduring.",
      "pt": "Ela sorriu calorosamente apesar da dor óbvia que estava suportando."
    },
    {
      "en": "The team won the championship despite being considered underdogs.",
      "pt": "A equipe ganhou o campeonato apesar de ser considerada a zebra."
    },
    {
      "en": "He remains a popular figure despite the recent political scandals.",
      "pt": "Ele permanece uma figura popular apesar dos recentes escândalos políticos."
    },
    {
      "en": "We enjoyed the hike despite the steep and rocky terrain.",
      "pt": "Nós gostamos da caminhada apesar do terreno íngreme e rochoso."
    },
    {
      "en": "She finished the marathon despite a nagging injury in her knee.",
      "pt": "Ela terminou a maratona apesar de uma lesão persistente no joelho."
    },
    {
      "en": "Despite his age, he is still incredibly sharp and active.",
      "pt": "Apesar da idade, ele ainda é incrivelmente perspicaz e ativo."
    },
    {
      "en": "The policy was implemented despite widespread public criticism.",
      "pt": "A política foi implementada apesar das críticas públicas generalizadas."
    },
    {
      "en": "They remained close friends despite their differing political views.",
      "pt": "Eles continuaram amigos íntimos apesar de suas visões políticas divergentes."
    },
    {
      "en": "She accepted the challenge despite the high probability of failure.",
      "pt": "Ela aceitou o desafio apesar da alta probabilidade de fracasso."
    },
    {
      "en": "The flower bloomed vibrantly despite the arid and harsh soil.",
      "pt": "A flor desabrochou vibrantemente apesar do solo árido e hostil."
    },
    {
      "en": "He slept soundly despite the cacophony of the city outside.",
      "pt": "Ele dormiu profundamente apesar da cacofonia da cidade lá fora."
    },
    {
      "en": "The agreement was signed despite lingering doubts about its viability.",
      "pt": "O acordo foi assinado apesar das dúvidas persistentes sobre sua viabilidade."
    },
    {
      "en": "She climbed the career ladder quickly despite facing systemic bias.",
      "pt": "Ela subiu na carreira rapidamente apesar de enfrentar viés sistêmico."
    },
    {
      "en": "Despite the delays, the launch was considered a resounding success.",
      "pt": "Apesar dos atrasos, o lançamento foi considerado um sucesso estrondoso."
    },
    {
      "en": "He kept his promise despite the personal cost involved.",
      "pt": "Ele manteve sua promessa apesar do custo pessoal envolvido."
    },
    {
      "en": "The antique car runs perfectly despite its advanced age.",
      "pt": "O carro antigo funciona perfeitamente apesar de sua idade avançada."
    },
    {
      "en": "She decided to stay despite the lucrative offer from a competitor.",
      "pt": "Ela decidiu ficar apesar da oferta lucrativa de um concorrente."
    },
    {
      "en": "Despite the risks, they ventured into the unknown territory.",
      "pt": "Apesar dos riscos, eles se aventuraram no território desconhecido."
    },
    {
      "en": "He stood by his decision despite the overwhelming backlash.",
      "pt": "Ele manteve sua decisão apesar da reação negativa avassaladora."
    },
    {
      "en": "The building stands firm despite centuries of exposure to the elements.",
      "pt": "O edifício permanece firme apesar de séculos de exposição aos elementos."
    },
    {
      "en": "She loves him dearly despite his many annoying flaws.",
      "pt": "Ela o ama muito apesar de seus muitos defeitos irritantes."
    },
    {
      "en": "We arrived on schedule despite the heavy traffic congestion.",
      "pt": "Chegamos no horário apesar do congestionamento de trânsito pesado."
    },
    {
      "en": "He mastered the language quickly despite its complex grammar rules.",
      "pt": "Ele dominou a língua rapidamente apesar de suas regras gramaticais complexas."
    },
    {
      "en": "Despite the controversy, the film received critical acclaim.",
      "pt": "Apesar da controvérsia, o filme recebeu aclamação da crítica."
    },
    {
      "en": "She remained silent despite the urge to defend herself.",
      "pt": "Ela permaneceu em silêncio apesar da vontade de se defender."
    },
    {
      "en": "They prospered despite the unfavorable economic climate.",
      "pt": "Eles prosperaram apesar do clima econômico desfavorável."
    },
    {
      "en": "He attended the meeting despite feeling under the weather.",
      "pt": "Ele compareceu à reunião apesar de não estar se sentindo bem."
    },
    {
      "en": "Despite the gloomy forecast, the sun shone all afternoon.",
      "pt": "Apesar da previsão sombria, o sol brilhou a tarde toda."
    },
    {
      "en": "She holds no grudges despite the way she was treated.",
      "pt": "Ela não guarda rancor apesar da maneira como foi tratada."
    },
    {
      "en": "The law was repealed despite the governor's veto attempt.",
      "pt": "A lei foi revogada apesar da tentativa de veto do governador."
    },
    {
      "en": "He found peace despite the chaos surrounding his personal life.",
      "pt": "Ele encontrou paz apesar do caos cercando sua vida pessoal."
    },
    {
      "en": "Despite the warnings, he ventured too close to the edge.",
      "pt": "Apesar dos avisos, ele se aventurou muito perto da borda."
    },
    {
      "en": "She appeared confident despite the trembling in her hands.",
      "pt": "Ela parecia confiante apesar do tremor em suas mãos."
    },
    {
      "en": "The software works well despite some minor bugs.",
      "pt": "O software funciona bem apesar de alguns bugs menores."
    },
    {
      "en": "He donated generously despite his own financial constraints.",
      "pt": "Ele doou generosamente apesar de suas próprias restrições financeiras."
    },
    {
      "en": "Despite the rumors, the company is not filing for bankruptcy.",
      "pt": "Apesar dos rumores, a empresa não está pedindo falência."
    },
    {
      "en": "She passed the exam despite having little time to study.",
      "pt": "Ela passou no exame apesar de ter pouco tempo para estudar."
    },
    {
      "en": "The species survives despite the destruction of its natural habitat.",
      "pt": "A espécie sobrevive apesar da destruição de seu habitat natural."
    },
    {
      "en": "He kept walking despite the exhaustion overtaking his body.",
      "pt": "Ele continuou andando apesar da exaustão tomando conta de seu corpo."
    },
    {
      "en": "Despite everything, they managed to build a happy life together.",
      "pt": "Apesar de tudo, eles conseguiram construir uma vida feliz juntos."
    }
  ],
  "pronunciationExercises": [
    {
      "question": "despite",
      "options": [
        "despise",
        "despite"
      ],
      "correct": "despite"
    },
    {
      "question": "despite",
      "options": [
        "despite",
        "respite"
      ],
      "correct": "despite"
    },
    {
      "question": "despite",
      "options": [
        "despite",
        "dispute"
      ],
      "correct": "despite"
    },
    {
      "question": "despite",
      "options": [
        "spite",
        "despite"
      ],
      "correct": "despite"
    },
    {
      "question": "despite",
      "options": [
        "despair",
        "despite"
      ],
      "correct": "despite"
    },
    {
      "question": "despite",
      "options": [
        "despite",
        "despise"
      ],
      "correct": "despite"
    },
    {
      "question": "despite",
      "options": [
        "respite",
        "despite"
      ],
      "correct": "despite"
    },
    {
      "question": "despite",
      "options": [
        "dispute",
        "despite"
      ],
      "correct": "despite"
    },
    {
      "question": "despite",
      "options": [
        "despite",
        "spite"
      ],
      "correct": "despite"
    },
    {
      "question": "despite",
      "options": [
        "despite",
        "despair"
      ],
      "correct": "despite"
    },
    {
      "question": "despite",
      "options": [
        "despise",
        "despite"
      ],
      "correct": "despite"
    },
    {
      "question": "despite",
      "options": [
        "despite",
        "respite"
      ],
      "correct": "despite"
    },
    {
      "question": "despite",
      "options": [
        "despite",
        "dispute"
      ],
      "correct": "despite"
    },
    {
      "question": "despite",
      "options": [
        "despite",
        "despise"
      ],
      "correct": "despite"
    },
    {
      "question": "despite",
      "options": [
        "spite",
        "despite"
      ],
      "correct": "despite"
    }
  ]
}
