{
  "sentences": [
    {
      "en": "Stock prices began to plummet after the negative announcement.",
      "pt": "Os preços das ações começaram a despencar após o anúncio negativo."
    },
    {
      "en": "The company's profits plummeted by 40% in the last quarter.",
      "pt": "Os lucros da empresa despencaram 40% no último trimestre."
    },
    {
      "en": "Temperatures are expected to plummet below freezing tonight.",
      "pt": "Espera-se que as temperaturas caiam vertiginosamente abaixo de zero esta noite."
    },
    {
      "en": "His approval ratings plummeted after the political scandal.",
      "pt": "Seus índices de aprovação despencaram após o escândalo político."
    },
    {
      "en": "The damaged aircraft plummeted into the ocean.",
      "pt": "A aeronave danificada mergulhou no oceano."
    },
    {
      "en": "We watched the hawk plummet from the sky to catch its prey.",
      "pt": "Observamos o falcão mergulhar do céu para pegar sua presa."
    },
    {
      "en": "The team's morale plummeted after their fifth consecutive loss.",
      "pt": "O moral da equipe despencou após a quinta derrota consecutiva."
    },
    {
      "en": "Consumer confidence plummeted to its lowest point in years.",
      "pt": "A confiança do consumidor caiu para o seu nível mais baixo em anos."
    },
    {
      "en": "The elevator plummeted five floors before the brakes engaged.",
      "pt": "O elevador despencou cinco andares antes que os freios fossem acionados."
    },
    {
      "en": "Her spirits plummeted when she heard she didn't get the job.",
      "pt": "O ânimo dela despencou quando ela ouviu que não conseguiu o emprego."
    },
    {
      "en": "Oil prices will plummet if global demand continues to fall.",
      "pt": "Os preços do petróleo irão despencar se a demanda global continuar a cair."
    },
    {
      "en": "The rock plummeted down the cliff face into the valley below.",
      "pt": "A rocha despencou pelo penhasco até o vale abaixo."
    },
    {
      "en": "Support for the new law has plummeted in recent polls.",
      "pt": "O apoio à nova lei despencou nas pesquisas recentes."
    },
    {
      "en": "The company's market share plummeted due to new competition.",
      "pt": "A participação de mercado da empresa despencou devido à nova concorrência."
    },
    {
      "en": "The stock's value plummeted, wiping out his life savings.",
      "pt": "O valor da ação despencou, aniquilando suas economias."
    },
    {
      "en": "His hopes of winning plummeted after the injury.",
      "pt": "Suas esperanças de vencer despencaram após a lesão."
    },
    {
      "en": "The bird's population plummeted because of the harsh winter.",
      "pt": "A população de pássaros despencou por causa do inverno rigoroso."
    },
    {
      "en": "Sales of the old model plummeted when the new one was released.",
      "pt": "As vendas do modelo antigo despencaram quando o novo foi lançado."
    },
    {
      "en": "The stunt driver plummeted off the ramp and over the buses.",
      "pt": "O piloto dublê mergulhou da rampa e por cima dos ônibus."
    },
    {
      "en": "My enthusiasm for the project plummeted after the budget cuts.",
      "pt": "Meu entusiasmo pelo projeto despencou após os cortes no orçamento."
    },
    {
      "en": "The meteor plummeted through the atmosphere at incredible speed.",
      "pt": "O meteoro mergulhou pela atmosfera em velocidade incrível."
    },
    {
      "en": "The quality of the show plummeted in its final season.",
      "pt": "A qualidade da série despencou em sua temporada final."
    },
    {
      "en": "We must act now to stop our profits from plummeting further.",
      "pt": "Devemos agir agora para impedir que nossos lucros caiam ainda mais."
    },
    {
      "en": "He felt his stomach plummet as the rollercoaster began to drop.",
      "pt": "Ele sentiu seu estômago despencar quando a montanha-russa começou a cair."
    },
    {
      "en": "The sudden plummet in sales took the company by surprise.",
      "pt": "A queda vertiginosa repentina nas vendas pegou a empresa de surpresa."
    },
    {
      "en": "The heavy anchor plummeted to the bottom of the sea.",
      "pt": "A âncora pesada despencou para o fundo do mar."
    },
    {
      "en": "The team's performance has plummeted since their star player retired.",
      "pt": "O desempenho da equipe despencou desde que seu jogador principal se aposentou."
    },
    {
      "en": "We watched the climber's gear plummet down the mountain.",
      "pt": "Observamos o equipamento do alpinista despencar montanha abaixo."
    },
    {
      "en": "Public trust in the government plummeted after the scandal.",
      "pt": "A confiança do público no governo despencou após o escândalo."
    },
    {
      "en": "The currency's value is plummeting against the dollar.",
      "pt": "O valor da moeda está despencando em relação ao dólar."
    },
    {
      "en": "The eagle will plummet from a great height to strike.",
      "pt": "A águia mergulhará de uma grande altura para atacar."
    },
    {
      "en": "His grades plummeted when he started skipping school.",
      "pt": "As notas dele despencaram quando ele começou a faltar à escola."
    },
    {
      "en": "The number of new subscriptions plummeted last month.",
      "pt": "O número de novas assinaturas despencou no mês passado."
    },
    {
      "en": "The damaged drone plummeted from the sky and crashed.",
      "pt": "O drone danificado despencou do céu e colidiu."
    },
    {
      "en": "Investor confidence plummeted, leading to a massive sell-off.",
      "pt": "A confiança dos investidores despencou, levando a uma liquidação massiva."
    },
    {
      "en": "His energy levels tend to plummet in the late afternoon.",
      "pt": "Seus níveis de energia tendem a despencar no final da tarde."
    },
    {
      "en": "We saw the wreckage of the plane plummet into the jungle.",
      "pt": "Vimos os destroços do avião despencarem na selva."
    },
    {
      "en": "The plummeting temperatures are a danger to the homeless population.",
      "pt": "A queda vertiginosa das temperaturas é um perigo para a população de rua."
    },
    {
      "en": "Attendance at the theme park plummeted during the rainy season.",
      "pt": "A frequência no parque temático despencou durante a estação chuvosa."
    },
    {
      "en": "A sudden illness caused his performance levels to plummet.",
      "pt": "Uma doença súbita fez com que seus níveis de desempenho despencassem."
    },
    {
      "en": "The heavy object plummeted through the thin ice.",
      "pt": "O objeto pesado afundou através do gelo fino."
    },
    {
      "en": "The plummeting birth rate is a concern for economists.",
      "pt": "A queda vertiginosa da taxa de natalidade é uma preocupação para os economistas."
    },
    {
      "en": "If we don't innovate, our market relevance will plummet.",
      "pt": "Se não inovarmos, nossa relevância no mercado despencará."
    },
    {
      "en": "The hero plummeted from the building, landing safely on the airbag.",
      "pt": "O herói despencou do prédio, aterrissando em segurança no airbag."
    },
    {
      "en": "The value of their assets plummeted overnight.",
      "pt": "O valor de seus ativos despencou da noite para o dia."
    },
    {
      "en": "The barometer reading plummeted, signaling a severe storm.",
      "pt": "A leitura do barômetro despencou, sinalizando uma tempestade severa."
    },
    {
      "en": "He watched his chances of victory plummet with each mistake.",
      "pt": "Ele viu suas chances de vitória despencarem a cada erro."
    },
    {
      "en": "The company's stock is plummeting in after-hours trading.",
      "pt": "As ações da empresa estão despencando nas negociações após o fechamento do mercado."
    },
    {
      "en": "The quality of service at that restaurant has really plummeted.",
      "pt": "A qualidade do serviço naquele restaurante realmente despencou."
    },
    {
      "en": "A diver will plummet headfirst into the water.",
      "pt": "Um mergulhador irá mergulhar de cabeça na água."
    }
  ],
  "pronunciationExercises": [
    {
      "question": "plummet",
      "options": [
        "plummet",
        "planet"
      ],
      "correct": "plummet"
    },
    {
      "question": "plummet",
      "options": [
        "plume",
        "plummet"
      ],
      "correct": "plummet"
    },
    {
      "question": "plummet",
      "options": [
        "plummet",
        "summit"
      ],
      "correct": "plummet"
    },
    {
      "question": "plummet",
      "options": [
        "comet",
        "plummet"
      ],
      "correct": "plummet"
    },
    {
      "question": "plummet",
      "options": [
        "plummet",
        "plump"
      ],
      "correct": "plummet"
    },
    {
      "question": "plummet",
      "options": [
        "permit",
        "plummet"
      ],
      "correct": "plummet"
    },
    {
      "question": "plummet",
      "options": [
        "planet",
        "plummet"
      ],
      "correct": "plummet"
    },
    {
      "question": "plummet",
      "options": [
        "plummet",
        "plume"
      ],
      "correct": "plummet"
    },
    {
      "question": "plummet",
      "options": [
        "summit",
        "plummet"
      ],
      "correct": "plummet"
    },
    {
      "question": "plummet",
      "options": [
        "plummet",
        "comet"
      ],
      "correct": "plummet"
    },
    {
      "question": "plummet",
      "options": [
        "plump",
        "plummet"
      ],
      "correct": "plummet"
    },
    {
      "question": "plummet",
      "options": [
        "plummet",
        "permit"
      ],
      "correct": "plummet"
    },
    {
      "question": "plummet",
      "options": [
        "planet",
        "plummet"
      ],
      "correct": "plummet"
    },
    {
      "question": "plummet",
      "options": [
        "plummet",
        "summit"
      ],
      "correct": "plummet"
    },
    {
      "question": "plummet",
      "options": [
        "comet",
        "plummet"
      ],
      "correct":"plummet"
    }
  ]
}
